django_country_and_language_flags-0.1.1.dist-info/METADATA
django_country_and_language_flags-0.1.1.dist-info/RECORD
django_country_and_language_flags-0.1.1.dist-info/WHEEL
django_country_and_language_flags-0.1.1.dist-info/top_level.txt
language_flags/__init__.py
language_flags/static/css/flags.css
language_flags/static/css/flags.min.css
language_flags/static/img/blank.png
language_flags/static/img/flags.png
language_flags/templates/language_flags/flagrow.html
language_flags/templatetags/__init__.py
language_flags/templatetags/language_flags_tags.py
