Metadata-Version: 2.1
Name: django-country-and-language-flags
Version: 0.1.1
Summary: Display country flags or sets of flags of nations where a particular language is spoken
Home-page: https://github.com/ktalik/django-country-and-language-flags
Author: Anselm Lingnau
Author-email: anselm@anselms.net
License: BSD License
Platform: UNKNOWN
Classifier: Environment :: Web Environment
Classifier: Framework :: Django
Classifier: Intended Audience :: Developers
Classifier: License :: OSI Approved :: BSD License
Classifier: Operating System :: OS Independent
Classifier: Programming Language :: Python
Classifier: Programming Language :: Python :: 3
Classifier: Programming Language :: Python :: 3.4
Classifier: Programming Language :: Python :: 3.5
Classifier: Programming Language :: Python :: 3.6
Classifier: Topic :: Internet :: WWW/HTTP
Classifier: Topic :: Internet :: WWW/HTTP :: Dynamic Content
